LICENSE
MANIFEST.in
Makefile
README.md
pyproject.toml
setup.py
evaluation/evaluate.py
evaluation/visualizations.ipynb
evaluation/resources/gpt_pred.txt
evaluation/resources/gpt_system_prompt_evaluation.txt
evaluation/results/gpt3.5-s100-t0/bleus.txt
evaluation/results/gpt3.5-s100-t0/codebleus.txt
evaluation/results/gpt3.5-s100-t0/summary.txt
evaluation/results/gpt3.5-s100-t0/tests.txt
evaluation/results/gpt3.5-s100-t0.5/bleus.txt
evaluation/results/gpt3.5-s100-t0.5/codebleus.txt
evaluation/results/gpt3.5-s100-t0.5/summary.txt
evaluation/results/gpt3.5-s100-t0.5/tests.txt
evaluation/results/gpt3.5-s100-t1/bleus.txt
evaluation/results/gpt3.5-s100-t1/codebleus.txt
evaluation/results/gpt3.5-s100-t1/summary.txt
evaluation/results/gpt3.5-s100-t1/tests.txt
evaluation/results/gpt3.5-s1000-t0/bleus.txt
evaluation/results/gpt3.5-s1000-t0/codebleus.txt
evaluation/results/gpt3.5-s1000-t0/summary.txt
evaluation/results/gpt3.5-s1000-t0/tests.txt
evaluation/results/gpt4-s100-t1/bleus.txt
evaluation/results/gpt4-s100-t1/codebleus.txt
evaluation/results/gpt4-s100-t1/summary.txt
evaluation/results/gpt4-s100-t1/tests.txt
genie/__init__.py
genie/main.py
genie/images/video-thumbnail.png
genie/parsers/ClassParser.py
genie/parsers/ConfigParser.py
genie/parsers/TestParser.py
genie/resources/generate_by_methods_prompt.txt
genie/resources/gpt_response_for_parsed.json
genie/resources/gpt_response_for_parsed_broken.json
genie/resources/gpt_response_for_raw.txt
genie/resources/gpt_system_prompt_parsed.txt
genie/resources/gpt_system_prompt_raw.txt
genie/resources/java-grammar.so
genie/resources/libtree-sitter-java.dylib
genie/wrappers/GptWrapper.py
java_test_genie.egg-info/PKG-INFO
java_test_genie.egg-info/SOURCES.txt
java_test_genie.egg-info/dependency_links.txt
java_test_genie.egg-info/entry_points.txt
java_test_genie.egg-info/top_level.txt
milestones/Final Report - Bora Elci.pdf
milestones/Project Progress Report - Bora Elci.pdf
milestones/Revised Project Proposal - Bora Elci.pdf
milestones/Slides link.txt