Metadata-Version: 2.1
Name: java-test-genie
Version: 1.0
Summary: AI-Driven Unit Test Generation for Java
Home-page: https://github.com/boraelci/java-test-genie
Author: Bora Elci
Author-email: bora.elci@columbia.edu
License: UNKNOWN
Platform: UNKNOWN
License-File: LICENSE
